daml_dit_api/__init__.py
daml_dit_api/integration_runtime_spec.py
daml_dit_api/package_metadata.py
daml_dit_api/py.typed
daml_dit_api-0.5.0.dist-info/LICENSE
daml_dit_api-0.5.0.dist-info/METADATA
daml_dit_api-0.5.0.dist-info/WHEEL
daml_dit_api-0.5.0.dist-info/RECORD
