Metadata-Version: 2.1
Name: daml-dit-api
Version: 0.5.0
Summary: Daml Hub DIT File API Package
Home-page: https://github.com/digital-asset/daml-dit-api
Keywords: daml,blockchain,dlt,distributed ledger,digital asset
Author: Mike Schaeffer
Author-email: mike.schaeffer@digitalasset.com
Requires-Python: >=3.8,<4.0
Classifier: Programming Language :: Python :: 3
Classifier: Programming Language :: Python :: 3.8
Classifier: Programming Language :: Python :: 3.9
Classifier: Programming Language :: Python :: 3.10
Classifier: Programming Language :: Python :: 3.11
Provides-Extra: develop
Project-URL: Repository, https://github.com/digital-asset/daml-dit-api
